setup.py
ncdu_s3/__init__.py
ncdu_s3/directory_walker.py
ncdu_s3/main.py
ncdu_s3/ncdu_data_writer.py
ncdu_s3/s3_directory_generator.py
ncdu_s3.egg-info/PKG-INFO
ncdu_s3.egg-info/SOURCES.txt
ncdu_s3.egg-info/dependency_links.txt
ncdu_s3.egg-info/entry_points.txt
ncdu_s3.egg-info/requires.txt
ncdu_s3.egg-info/top_level.txt