Metadata-Version: 1.1
Name: ncdu-s3
Version: 0.2
Summary: Generate ncdu data files for S3 buckets
Home-page: http://github.com/EverythingMe/ncdu-s3
Author: EverythingMe
Author-email: omrib@everything.me
License: UNKNOWN
Platform: UNKNOWN
Classifier: Development Status :: 5 - Production/Stable
Classifier: Environment :: Console
Classifier: Intended Audience :: Developers
Classifier: Intended Audience :: System Administrators
Classifier: Operating System :: OS Independent
Classifier: Programming Language :: Python :: 2.7
Classifier: Topic :: System :: Systems Administration
Classifier: Topic :: Utilities
